pythonasciitree/__init__.py
pythonasciitree/pythonasciitree.py
pythonasciitree-0.1.dist-info/METADATA
pythonasciitree-0.1.dist-info/WHEEL
pythonasciitree-0.1.dist-info/top_level.txt
pythonasciitree-0.1.dist-info/RECORD
