Metadata-Version: 2.1
Name: pythonasciitree
Version: 0.1
Summary: Simple Ascii Art Tree
Author: Jessi Flessi
Author-email: jessehoekema@icloud.com
Classifier: Programming Language :: Python :: 3
Classifier: License :: OSI Approved :: MIT License
Classifier: Operating System :: OS Independent
Requires-Python: >=3.6
